binaryduino/__init__.py
binaryduino/core.py
binaryduino-0.1.0.dist-info/licenses/LICENSE
binaryduino-0.1.0.dist-info/METADATA
binaryduino-0.1.0.dist-info/WHEEL
binaryduino-0.1.0.dist-info/entry_points.txt
binaryduino-0.1.0.dist-info/top_level.txt
binaryduino-0.1.0.dist-info/RECORD
