Metadata-Version: 2.4
Name: binaryduino
Version: 0.1.0
Summary: Binary and Arduino simulation toolkit with waveform visualization and signal processing
Home-page: https://github.com/EdenGithhub/binaryduino
Author: Adam Alcander et Eden
Author-email: aeden6877@gmail.com
License: MIT
Classifier: Programming Language :: Python :: 3.7
Classifier: Programming Language :: Python :: 3.8
Classifier: Programming Language :: Python :: 3.9
Classifier: Programming Language :: Python :: 3.10
Classifier: Programming Language :: Python :: 3.11
Classifier: Programming Language :: Python :: 3.12
Classifier: Programming Language :: Python :: 3.13
Classifier: License :: OSI Approved :: MIT License
Classifier: Operating System :: OS Independent
Requires-Python: >=3.7
License-File: LICENSE
Requires-Dist: numpy
Requires-Dist: matplotlib
Requires-Dist: colorama
Requires-Dist: bitstring
Requires-Dist: pyserial
Requires-Dist: loguru
Requires-Dist: rich
Requires-Dist: pydantic
Requires-Dist: typer
Requires-Dist: tqdm
Requires-Dist: python-dotenv
Requires-Dist: click
Dynamic: author
Dynamic: author-email
Dynamic: classifier
Dynamic: description
Dynamic: description-content-type
Dynamic: home-page
Dynamic: license
Dynamic: license-file
Dynamic: requires-dist
Dynamic: requires-python
Dynamic: summary
